{
    "classification": "electronic",
    "type": "header",
    "size": "2d54_mm_dual_row",
    "color": "",
    "description_main": "2x12_dual_row_24_pin",
    "description_extra": "",
    "manufacturer": "",
    "part_number": "",
    "make_files": true,
    "kicad_reference": "J",
    "id": "electronic_header_2d54_mm_dual_row_2x12_dual_row_24_pin",
    "oomp_key": "oomp_electronic_header_2d54_mm_dual_row_2x12_dual_row_24_pin",
    "directory": "parts/electronic_header_2d54_mm_dual_row_2x12_dual_row_24_pin",
    "name": "Electronic Header 2D54 Mm Dual Row 2X12 Dual Row 24 Pin",
    "short_code": "h",
    "distributors": [],
    "md5": "52b4b3ebf2624d0b04e5badd2c6da75d",
    "md5_5": "52b4b",
    "md5_6": "52b4b3",
    "md5_10": "52b4b3ebf2"
}