{
    "classification": "electronic",
    "type": "header",
    "size": "2d54_mm",
    "color": "",
    "description_main": "26_pin",
    "description_extra": "surface_mount_right_angle",
    "manufacturer": "",
    "part_number": "",
    "make_files": true,
    "kicad_reference": "J",
    "id": "electronic_header_2d54_mm_26_pin_surface_mount_right_angle",
    "oomp_key": "oomp_electronic_header_2d54_mm_26_pin_surface_mount_right_angle",
    "directory": "parts/electronic_header_2d54_mm_26_pin_surface_mount_right_angle",
    "name": "Electronic Header 2D54 Mm 26 Pin Surface Mount Right Angle",
    "short_code": "hi126p26p",
    "short_name": "0.1\" 26 Pin Surface Mount Right Angle Header",
    "distributors": [],
    "md5": "e1c357d34bd8fdc17537c9d39a984907",
    "md5_5": "e1c35",
    "md5_6": "e1c357",
    "md5_10": "e1c357d34b"
}