{
    "classification": "electronic",
    "type": "resistor",
    "size": "0603",
    "color": "",
    "description_main": "82_ohm",
    "description_extra": "",
    "manufacturer": "",
    "part_number": "",
    "from_yaml": false,
    "make_files": true,
    "filter": "",
    "kicad_reference": "R",
    "id": "electronic_resistor_0603_82_ohm",
    "oomp_key": "oomp_electronic_resistor_0603_82_ohm",
    "github_link": "https://github.com/oomlout/oomlout_oomp_part_src/tree/main/parts/electronic_resistor_0603_82_ohm/working",
    "directory": "parts/electronic_resistor_0603_82_ohm",
    "name": "Electronic Resistor 0603 82 Ohm",
    "short_code": "r6o820",
    "distributors": [],
    "manufacturers": [],
    "package_style": "smd_tape",
    "smd_tape_width": "8_mm",
    "smd_tape_depth": "1_5_mm",
    "smd_tape_pitch": "4_mm",
    "md5": "825d758ddacd4f1e05a6eb369c752271",
    "md5_5": "825d7",
    "md5_6": "825d75",
    "md5_10": "825d758dda",
    "markdown_full": "[electronic_resistor_0603_82_ohm](https://github.com/oomlout/oomlout_oomp_part_src/tree/main/parts/electronic_resistor_0603_82_ohm/working)<br>[r6o820](https://github.com/oomlout/oomlout_oomp_part_src/tree/main/parts/electronic_resistor_0603_82_ohm/working)<br><br>"
}