{
    "classification": "electronic",
    "type": "crystal",
    "size": "3215",
    "color": "2_pin",
    "description_main": "12_mega_hertz",
    "description_extra": "",
    "manufacturer": "",
    "part_number": "",
    "from_yaml": false,
    "make_files": true,
    "filter": "",
    "kicad_reference": "x",
    "id": "electronic_crystal_3215_2_pin_12_mega_hertz",
    "oomp_key": "oomp_electronic_crystal_3215_2_pin_12_mega_hertz",
    "directory": "parts/electronic_crystal_3215_2_pin_12_mega_hertz",
    "name": "Electronic Crystal 3215 2 Pin 12 Mega Hertz",
    "short_code": "x3215mhz12",
    "distributors": [],
    "md5": "0580c994ab3f388e5cb32a4be729d265",
    "md5_5": "0580c",
    "md5_6": "0580c9",
    "md5_10": "0580c994ab"
}