{
    "classification": "electronic",
    "type": "header",
    "size": "1_mm_jst_sh",
    "color": "",
    "description_main": "4_pin",
    "description_extra": "surface_mount",
    "manufacturer": "",
    "part_number": "",
    "make_files": true,
    "kicad_reference": "J",
    "id": "electronic_header_1_mm_jst_sh_4_pin_surface_mount",
    "oomp_key": "oomp_electronic_header_1_mm_jst_sh_4_pin_surface_mount",
    "directory": "parts/electronic_header_1_mm_jst_sh_4_pin_surface_mount",
    "name": "Electronic Header 1 Mm Jst Sh 4 Pin Surface Mount",
    "short_code": "h4p4p",
    "short_name": "Jst Sh 4 Pin Surface Mount Header 1 Mm Pitch",
    "distributors": [],
    "md5": "a679e860a819577244ae5cd400e79203",
    "md5_5": "a679e",
    "md5_6": "a679e8",
    "md5_10": "a679e860a8"
}